encryptool/__init__.py
encryptool/__main__.py
encryptool/cli.py
encryptool/crypto/__init__.py
encryptool/crypto/dna.py
encryptool/crypto/rsa.py
encryptool/utils/__init__.py
encryptool/utils/parser.py
encryptool-1.1.0.dist-info/METADATA
encryptool-1.1.0.dist-info/WHEEL
encryptool-1.1.0.dist-info/entry_points.txt
encryptool-1.1.0.dist-info/licenses/LICENCE
encryptool-1.1.0.dist-info/RECORD
